{"lock_version":7,"title":"Test University Collection","other_level":"Collection","publish":false,"restrictions":true,"ead_id":"0012_0000_0000","finding_aid_title":"Test University Collection ","finding_aid_date":"2019","finding_aid_author":"Alesha Shumar","finding_aid_language":"English ","created_by":"alesha","last_modified_by":"alesha","create_time":"2019-05-13T14:57:38Z","system_mtime":"2019-05-13T18:16:31Z","user_mtime":"2019-05-13T18:16:31Z","suppressed":false,"id_0":"AR","id_1":"0000","language":"eng","level":"file","resource_type":"collection","finding_aid_description_rules":"dacs","finding_aid_status":"in_progress","jsonmodel_type":"resource","external_ids":[],"subjects":[],"linked_events":[],"extents":[{"lock_version":0,"number":"2","created_by":"alesha","last_modified_by":"alesha","create_time":"2019-05-13T18:16:31Z","system_mtime":"2019-05-13T18:16:31Z","user_mtime":"2019-05-13T18:16:31Z","portion":"whole","extent_type":"linear_foot","jsonmodel_type":"extent"}],"dates":[{"lock_version":0,"expression":"2002-2013","begin":"2002","end":"2012","created_by":"alesha","last_modified_by":"alesha","create_time":"2019-05-13T18:16:31Z","system_mtime":"2019-05-13T18:16:31Z","user_mtime":"2019-05-13T18:16:31Z","date_type":"inclusive","label":"creation","jsonmodel_type":"date"}],"external_documents":[],"rights_statements":[],"linked_agents":[],"revision_statements":[],"instances":[],"deaccessions":[],"related_accessions":[],"classifications":[],"notes":[],"uri":"/repositories/2/resources/5499","repository":{"ref":"/repositories/2"},"tree":{"ref":"/repositories/2/resources/5499/tree"}}
